{
  "_说明": "本文件用于配置 xlsx_to_prospect_json.py 的输入、输出、字段映射等。修改后无需改代码即可生效。所有路径支持绝对路径，相对路径以脚本所在目录为基准。带 _ 开头的 key 全部是注释字段，运行时会被忽略。",
  "输入": {
    "_说明": "backup_dir 是 Excel 备份目录；filename_pattern 用于在该目录中筛选文件并提取时间戳。脚本默认按文件名时间戳挑最新的 .xlsx，没匹配到时退化为按 mtime 最新者。",
    "backup_dir": "X:\\backup\\ProspectiveContacts",
    "filename_pattern": "^/意向专用通讯录导出_(\\d{8})_(\\d{6})(?:_\\d+)?\\.xlsx$",
    "sheet_index": 0
  },
  "输出": {
    "_说明": "默认结果文件落到脚本同目录（output_dir = '.'）。改成绝对路径或相对路径都可以；相对路径相对脚本所在目录。带时间戳的快照通过 save_timestamped_copy 控制，默认开启，便于回溯历史。",
    "output_dir": ".",
    "json_filename": "意向通讯录.json",
    "save_timestamped_copy": true,
    "timestamped_filename_template": "logs/意向通讯录_{timestamp}.json",
    "indent": 2
  },
  "Excel表头": {
    "_说明": "下列键是脚本内部使用的字段名，值是 Excel 表头里真实的列名。Excel 列名调整时只改这里。本字段映射严格按列名查找（不依赖列顺序），若 Excel 调整顺序也仍然有效。",
    "学员微信号列": "意向学员(微信号)",
    "学员微信原始ID列": "意向学员(微信ID)",
    "学员是否删除列": "意向学员(是否删除)",
    "推荐人微信号列": "来源(微信号)",
    "推荐人微信原始ID列": "来源(微信ID)",
    "绑定时间列": "意向学员(添加时间)"
  },
  "输出字段名": {
    "_说明": "下列键是脚本内部使用的字段名，值是最终输出 JSON 里使用的 key。想改输出 JSON 的字段名，只改这里。",
    "学员对象": {
      "学员微信号": "意向学员微信号",
      "学员微信原始ID": "意向学员微信原始ID",
      "是否报名": "是否报名",
      "推荐人列表": "推荐人"
    },
    "推荐人对象": {
      "推荐人微信号": "推荐人微信号",
      "推荐人微信原始ID": "推荐人微信原始ID",
      "绑定日期": "绑定日期",
      "解绑日期": "解绑日期",
      "绑定状态": "绑定状态"
    }
  },
  "默认值": {
    "_说明": "Excel 没有提供的字段使用下方默认值。绑定状态_未删除 适用于学员未删除（=❌）的情况；绑定状态_已删除 适用于学员已删除（=✅）的情况。任意字段值留空字符串时，脚本会从输出 JSON 中省略该字段（解绑日期 / 绑定状态）。",
    "是否报名": "",
    "解绑日期": "",
    "绑定状态_未删除": "",
    "绑定状态_已删除": ""
  }
}
